<?xml version="1.0" encoding="UTF-8"?>
<BOXES> 										<!-- Root Element(Parent) -->
	<SECTION> 										<!-- Child Element -->
		<SECTIONTITLE>Erhvervserfaring</SECTIONTITLE> 	<!-- Sub-Child Element -->
			<BOX>
				<TITLE>StudioMetropolis</TITLE>
				<HEADER>This is a header.</HEADER>
				<BODYTXT>Filler text</BODYTXT>
				<FOOTER>This is a footer.</FOOTER>
			</BOX>
			<BOX>
				<TITLE>Avior</TITLE>
				<HEADER>This is a header.</HEADER>
				<BODYTXT>Filler text</BODYTXT>
				<FOOTER>This is a footer.</FOOTER>
			</BOX>
	</SECTION>
	<SECTION>
		<SECTIONTITLE>GameIT College - HTX</SECTIONTITLE>
			<BOX>
				<TITLE>Bogstaveligt Talt</TITLE>
				<HEADER>This is a header.</HEADER>
				<BODYTXT>Filler text</BODYTXT>
				<FOOTER>This is a footer.</FOOTER>
			</BOX>
			<BOX>
				<TITLE>Red Et Liv</TITLE>
				<HEADER>This is a header.</HEADER>
				<BODYTXT>Filler text</BODYTXT>
				<FOOTER>This is a footer.</FOOTER>
			</BOX>
			<BOX>
				<TITLE>Suit Pursuit</TITLE>
				<HEADER>This is a header.</HEADER>
				<BODYTXT>Filler text</BODYTXT>
				<FOOTER>This is a footer.</FOOTER>
			</BOX>
			<BOX>
				<TITLE>Arduino Pong</TITLE>
				<HEADER>This is a header.</HEADER>
				<BODYTXT>Filler text</BODYTXT>
				<FOOTER>This is a footer.</FOOTER>
			</BOX>
	</SECTION>
</BOXES>
